multiword_tokenization/__init__.py
multiword_tokenization/tokenize.py
multiword_tokenization-0.1.0a2.dist-info/DESCRIPTION.rst
multiword_tokenization-0.1.0a2.dist-info/METADATA
multiword_tokenization-0.1.0a2.dist-info/RECORD
multiword_tokenization-0.1.0a2.dist-info/WHEEL
multiword_tokenization-0.1.0a2.dist-info/metadata.json
multiword_tokenization-0.1.0a2.dist-info/top_level.txt
