Metadata-Version: 2.0
Name: multiword-tokenization
Version: 0.1.0a2
Summary: Multi-word tokenization
Home-page: https://github.com/katsuya-horiuchi/multiword_tokenization
Author: Katsuya Horiuchi
Author-email: katsuya.horiuchi.biz@gmail.com
License: Apache Software License
Keywords: NLP,tokenization
Platform: UNKNOWN
Classifier: Development Status :: 3 - Alpha
Classifier: License :: OSI Approved :: Apache Software License
Classifier: Intended Audience :: Developers
Classifier: Intended Audience :: Science/Research
Classifier: Natural Language :: English
Classifier: Programming Language :: Python
Classifier: Programming Language :: Python :: Implementation :: CPython
Classifier: Programming Language :: Python :: 2
Classifier: Programming Language :: Python :: 2.7
Classifier: Programming Language :: Python :: 3
Classifier: Programming Language :: Python :: 3.5
Classifier: Programming Language :: Python :: 3.6
